zmyzheng/__init__.py
zmyzheng/amlpipeline/AMLPipeline.py
zmyzheng/amlpipeline/HttpTriggeredPipeline.py
zmyzheng/amlpipeline/__init__.py
aml_pipeline-0.0.1.dist-info/LICENSE
aml_pipeline-0.0.1.dist-info/METADATA
aml_pipeline-0.0.1.dist-info/WHEEL
aml_pipeline-0.0.1.dist-info/top_level.txt
aml_pipeline-0.0.1.dist-info/RECORD
