Metadata-Version: 2.1
Name: aml-pipeline
Version: 0.0.1
Summary: Azure Machine Learning Pipeline high level API
Home-page: https://github.com/zmyzheng/Azure-ML-Pipeline
Author: Mingyang Zheng
Author-email: zhengzmy@gmail.com
License: UNKNOWN
Platform: UNKNOWN
Classifier: Programming Language :: Python :: 3
Classifier: License :: OSI Approved :: MIT License
Classifier: Operating System :: OS Independent
Requires-Python: >=3.6
Requires-Dist: azure-mgmt-resource (==10.2.0)
Requires-Dist: pyjwt (==1.7.1)
Requires-Dist: azureml-sdk (==1.12.0)
